js/__init__.py
js/core/__init__.py
js/core/array.py
js/core/console.py
js/core/require.py
js/core/string.py
js.py-2.0.0.dist-info/LICENSE
js.py-2.0.0.dist-info/METADATA
js.py-2.0.0.dist-info/WHEEL
js.py-2.0.0.dist-info/top_level.txt
js.py-2.0.0.dist-info/RECORD
