Metadata-Version: 2.1
Name: js.py
Version: 2.0.0
Summary: A library that extends Python base classes with their JavaScript default methods.
Home-page: https://github.com/nanipy/js.py
Author: Jens Reidel
Author-email: adrian@travitia.xyz
License: MIT
Platform: UNKNOWN
Classifier: Programming Language :: Python :: 3
Classifier: License :: OSI Approved :: MIT License
Classifier: Operating System :: OS Independent
Requires-Dist: forbiddenfruit
